xspass/__init__.py
xspass/generator.py
xspass-0.1.dist-info/METADATA
xspass-0.1.dist-info/WHEEL
xspass-0.1.dist-info/RECORD
