Metadata-Version: 2.4
Name: xspass
Version: 0.1
Summary: Модуль для генерации паролей
Project-URL: Homepage, https://github.com/XasdesNew/xspass
Author-email: XasdesNew <xasdesnew@gmail.com>
Classifier: License :: OSI Approved :: MIT License
Classifier: Operating System :: OS Independent
Classifier: Programming Language :: Python :: 3
Requires-Python: >=3.10
